vispy/__init__.py
vispy/conftest.py
vispy/version.py
vispy/app/__init__.py
vispy/app/_default_app.py
vispy/app/_detect_eventloop.py
vispy/app/application.py
vispy/app/base.py
vispy/app/canvas.py
vispy/app/qt.py
vispy/app/timer.py
vispy/app/backends/__init__.py
vispy/app/backends/_egl.py
vispy/app/backends/_glfw.py
vispy/app/backends/_jupyter_rfb.py
vispy/app/backends/_offscreen_util.py
vispy/app/backends/_osmesa.py
vispy/app/backends/_pyglet.py
vispy/app/backends/_pyqt4.py
vispy/app/backends/_pyqt5.py
vispy/app/backends/_pyqt6.py
vispy/app/backends/_pyside.py
vispy/app/backends/_pyside2.py
vispy/app/backends/_pyside6.py
vispy/app/backends/_qt.py
vispy/app/backends/_sdl2.py
vispy/app/backends/_template.py
vispy/app/backends/_test.py
vispy/app/backends/_tk.py
vispy/app/backends/_wx.py
vispy/app/backends/tests/__init__.py
vispy/app/backends/tests/test_offscreen_util.py
vispy/app/backends/tests/test_rfb.py
vispy/app/tests/__init__.py
vispy/app/tests/qt-designer.ui
vispy/app/tests/test_app.py
vispy/app/tests/test_backends.py
vispy/app/tests/test_canvas.py
vispy/app/tests/test_context.py
vispy/app/tests/test_qt.py
vispy/app/tests/test_simultaneous.py
vispy/color/__init__.py
vispy/color/_color_dict.py
vispy/color/color_array.py
vispy/color/color_space.py
vispy/color/colormap.py
vispy/color/tests/__init__.py
vispy/color/tests/test_color.py
vispy/ext/__init__.py
vispy/ext/cocoapy.py
vispy/ext/cubehelix.py
vispy/ext/egl.py
vispy/ext/fontconfig.py
vispy/ext/gdi32plus.py
vispy/ext/osmesa.py
vispy/geometry/__init__.py
vispy/geometry/_triangulation_debugger.py
vispy/geometry/calculations.py
vispy/geometry/curves.py
vispy/geometry/generation.py
vispy/geometry/isocurve.py
vispy/geometry/isosurface.py
vispy/geometry/meshdata.py
vispy/geometry/normals.py
vispy/geometry/parametric.py
vispy/geometry/polygon.py
vispy/geometry/rect.py
vispy/geometry/torusknot.py
vispy/geometry/triangulation.py
vispy/geometry/tests/__init__.py
vispy/geometry/tests/test_calculations.py
vispy-0.16.1.dist-info/licenses/LICENSE.txt
vispy-0.16.1.dist-info/METADATA
vispy-0.16.1.dist-info/WHEEL
vispy-0.16.1.dist-info/top_level.txt
vispy-0.16.1.dist-info/RECORD
